mist/__init__.py
mist/__main__.py
mist/files.py
mist/guuid.py
mist/net_utils.py
mist/validators.py
mist/action_run/__init__.py
mist/action_run/cli.py
mist/action_run/helpers.py
mist/action_run/interpreter.py
mist/action_run/language_tools.py
mist/action_server/__init__.py
mist/action_server/cli.py
mist/action_server/editor.py
mist/action_server/helpers.py
mist/action_server/realtime.py
mist/action_server/server.py
mist/action_server/storage.py
mist/action_server/templates/index.html
mist/action_server/templates/mode-mist.js
mist/catalog/S3Store.mist
mist/catalog/festin.mist
mist/catalog/filterRepeated.mist
mist/catalog/findOpenPorts.mist
mist/catalog/gitLeaksFinder.mist
mist/catalog/kafkaConsumer.mist
mist/catalog/kafkaProducer.mist
mist/catalog/mongoWatch.mist
mist/catalog/pythonCodeAnalysis.mist
mist/catalog/searchDomains.mist
mist/catalog/tail.mist
mist/catalog/trelloNewCard.mist
mist/lang/__init__.py
mist/lang/classes.py
mist/lang/cmd.py
mist/lang/config.py
mist/lang/core.tx
mist/lang/environment.py
mist/lang/exceptions.py
mist/lang/function.py
mist/lang/herlpers.py
mist/lang/params.py
mist/lang/streams.py
test/__init__.py
test/conftest.py
test/utilTest.py
test/integration/__init__.py
test/integration/test_CustomDict.py
test/integration/test_CustomList.py
test/integration/test_abort_example.py
test/integration/test_bool_func_if.py
test/integration/test_call_methods.py
test/integration/test_done.py
test/integration/test_exec.py
test/integration/test_exec_line_by_line.py
test/integration/test_filterDict.py
test/integration/test_formatted_string.py
test/integration/test_function_as_command.py
test/integration/test_function_definition.py
test/integration/test_function_nested.py
test/integration/test_function_range.py
test/integration/test_function_tmpFile.py
test/integration/test_function_with_named_args.py
test/integration/test_if_command.py
test/integration/test_import.py
test/integration/test_import_remote.py
test/integration/test_include.py
mist_lang-0.3.9.dist-info/LICENSE
mist_lang-0.3.9.dist-info/METADATA
mist_lang-0.3.9.dist-info/NOTICE
mist_lang-0.3.9.dist-info/WHEEL
mist_lang-0.3.9.dist-info/entry_points.txt
mist_lang-0.3.9.dist-info/top_level.txt
mist_lang-0.3.9.dist-info/zip-safe
mist_lang-0.3.9.dist-info/RECORD
