Metadata-Version: 2.1
Name: mist-lang
Version: 0.3.9
Summary: programming language for security made easy
Home-page: https://github.com/bbva/mist
License: License :: OSI Approved :: MIT
Platform: UNKNOWN
Classifier: Programming Language :: Python :: 3.8
Requires-Dist: textx
Requires-Dist: jsonpath-ng
Requires-Dist: terminaltables
Requires-Dist: flask
Requires-Dist: redis
Requires-Dist: flask-sse
Requires-Dist: flask-executor
Requires-Dist: httpx
